iMatic/__init__.py
iMatic/devices.py
iMatic-0.2.dist-info/LICENSE
iMatic-0.2.dist-info/METADATA
iMatic-0.2.dist-info/WHEEL
iMatic-0.2.dist-info/top_level.txt
iMatic-0.2.dist-info/RECORD
