Metadata-Version: 2.1
Name: iMatic
Version: 0.2
Summary: iMatic client library for 8/16 channel relay board controllers by SainSmart
Home-page: https://github.com/rp3tya/iMatic
Author: rp3tya
Author-email: rpetya@hotmail.com
License: UNKNOWN
Keywords: sainsmart imatic relay
Platform: UNKNOWN
Classifier: Programming Language :: Python :: 3
Classifier: License :: OSI Approved :: MIT License
Classifier: Operating System :: OS Independent
